tinypost/__init__.py
tinypost/_functions.py
tinypost/_grammar.py
tinypost/_postfix_parser.py
tinypost/_shunting_yard.py
tinypost/_test.py
tinypost-0.0.3.dist-info/LICENSE
tinypost-0.0.3.dist-info/METADATA
tinypost-0.0.3.dist-info/WHEEL
tinypost-0.0.3.dist-info/top_level.txt
tinypost-0.0.3.dist-info/RECORD
