Metadata-Version: 2.1
Name: tinypost
Version: 0.0.3
Summary: An infix-to-postfix expression parser for evaluating math expressions.
Home-page: UNKNOWN
Author: Nathan Abraham
Author-email: abnathan123@gmail.com
License: UNKNOWN
Keywords: python,math,shunting-yard,parser,expression evaluation
Platform: UNKNOWN
Classifier: Operating System :: Unix
Classifier: Operating System :: MacOS :: MacOS X
Classifier: Operating System :: Microsoft :: Windows
License-File: LICENSE
